pluploader/__init__.py
pluploader/__main__.py
pluploader/confluence/__init__.py
pluploader/confluence/jobs/__init__.py
pluploader/confluence/jobs/jobs.py
pluploader/job.py
pluploader/license.py
pluploader/main.py
pluploader/mpac/__init__.py
pluploader/mpac/download.py
pluploader/mpac/exceptions.py
pluploader/mpac/rest.py
pluploader/mpac/scraper.py
pluploader/safemode.py
pluploader/upm/__init__.py
pluploader/upm/exceptions.py
pluploader/upm/upmapi.py
pluploader/upm/upmcloudapi.py
pluploader/util/__init__.py
pluploader/util/atlassian_jar.py
pluploader/util/browser.py
pluploader/util/pathutil.py
pluploader-0.8.3.dist-info/LICENSE
pluploader-0.8.3.dist-info/METADATA
pluploader-0.8.3.dist-info/WHEEL
pluploader-0.8.3.dist-info/entry_points.txt
pluploader-0.8.3.dist-info/RECORD
