Metadata-Version: 2.1
Name: pluploader
Version: 0.8.3
Summary: CLI Confluence/Jira Plugin uploader
Home-page: https://github.com/livelyapps/pluploader
License: Apache-2.0
Author: Fabian Siegel
Author-email: fabian@livelyapps.com
Requires-Python: >=3.8,<4.0
Classifier: License :: OSI Approved :: Apache Software License
Classifier: Programming Language :: Python :: 3
Classifier: Programming Language :: Python :: 3.8
Classifier: Programming Language :: Python :: 3.9
Classifier: Programming Language :: Python :: 3.10
Classifier: Programming Language :: Python :: 3.11
Requires-Dist: PyYAML (>=6.0.1,<7.0.0)
Requires-Dist: beautifulsoup4 (>=4.9.3,<5.0.0)
Requires-Dist: click_default_group (>=1.2.2,<2.0.0)
Requires-Dist: colorama (>=0.4.3,<0.5.0)
Requires-Dist: configargparse (>=1.2.3,<2.0.0)
Requires-Dist: furl (>=2.1.0,<3.0.0)
Requires-Dist: html5lib (>=1.1,<2.0)
Requires-Dist: importlib-metadata (>=4.8.1,<5.0.0)
Requires-Dist: lxml (>=4.5.2,<5.0.0)
Requires-Dist: packaging (>=20.4,<21.0)
Requires-Dist: pydantic (>=1.6.1,<2.0.0)
Requires-Dist: requests (>=2.24.0,<3.0.0)
Requires-Dist: rich (>=9.5.1,<10.0.0)
Requires-Dist: typer (>=0.3.2,<0.4.0)
Project-URL: Repository, https://github.com/livelyapps/pluploader
